blueness/__init__.py
blueness/__main__.py
blueness/module.py
blueness/pypi.py
blueness/urls.py
blueness/.abcli/actions.sh
blueness/.abcli/blueness.sh
blueness/argparse/__init__.py
blueness/argparse/generic.py
blueness-3.118.1.dist-info/licenses/LICENSE
blueness-3.118.1.dist-info/METADATA
blueness-3.118.1.dist-info/WHEEL
blueness-3.118.1.dist-info/top_level.txt
blueness-3.118.1.dist-info/RECORD
